aiola/__init__.py
aiola/client.py
aiola/constants.py
aiola/errors.py
aiola/http_client.py
aiola/mic.py
aiola/types.py
aiola/clients/auth/__init__.py
aiola/clients/auth/client.py
aiola/clients/stt/__init__.py
aiola/clients/stt/client.py
aiola/clients/stt/stream_client.py
aiola/clients/tts/__init__.py
aiola/clients/tts/client.py
aiola-0.4.0.dist-info/METADATA
aiola-0.4.0.dist-info/WHEEL
aiola-0.4.0.dist-info/licenses/LICENSE
aiola-0.4.0.dist-info/RECORD
