Metadata-Version: 2.4
Name: aiola
Version: 0.4.0
Summary: The official Python SDK for aiOla API - Speech-to-Text and Text-to-Speech
Project-URL: Homepage, https://aiola.ai
Project-URL: Repository, https://github.com/aiola-lab/aiola-python-sdk
Project-URL: Bug Tracker, https://github.com/aiola-lab/aiola-python-sdk/issues
Author-email: aiOla <support@aiola.ai>
Maintainer-email: aiOla <support@aiola.ai>
License: MIT License
License-File: LICENSE
Keywords: aiola,audio,microphone,speech,speech-to-text,stt,text-to-speech,tts
Classifier: Development Status :: 5 - Production/Stable
Classifier: Intended Audience :: Developers
Classifier: License :: OSI Approved :: MIT License
Classifier: Operating System :: OS Independent
Classifier: Programming Language :: Python :: 3
Classifier: Programming Language :: Python :: 3.10
Classifier: Programming Language :: Python :: 3.11
Classifier: Programming Language :: Python :: 3.12
Classifier: Topic :: Multimedia :: Sound/Audio :: Speech
Classifier: Topic :: Software Development :: Libraries :: Python Modules
Requires-Python: >=3.10
Requires-Dist: httpx>=0.27
Requires-Dist: python-socketio[client]>=5.11
Provides-Extra: mic
Requires-Dist: numpy>=2.2.6; extra == 'mic'
Requires-Dist: sounddevice>=0.5.2; extra == 'mic'
